{
  "studyOrder": 13,
  "slug": "knee-high-stocking",
  "gwcSkillNumber": 2,
  "title": "Applies One Knee-High Compression Stocking (Ted Hose)",
  "stepCount": 11,
  "sourceSection": "S13",
  "selfScore": {
    "rubricFidelity": "PASS",
    "studentExecution": "PASS",
    "consistency": "PASS",
    "confidence": 97,
    "residualRisk": "is step 8 wording \"Move foot/leg gently; avoid force\" which condenses \"naturally\" and \"over-extension\"; Detailed Tag Text preserves the full rubric language"
  },
  "steps": [
    {
      "id": 1,
      "segment": "open",
      "stepText": "Introduce and explain procedure",
      "detailedTagText": "Introduce yourself by name and title, explain the procedure to the patient in clear, plain language, and obtain verbal consent before proceeding.",
      "tagCategory": "Opening",
      "phaseWord": "Approach",
      "clinicalNote": "",
      "subSteps": [],
      "criticalCategory": "",
      "examScorecard": "",
      "icon": "🟢🗣️",
      "boilerplateId": "INTRO_EXPLAIN"
    },
    {
      "id": 2,
      "segment": "open",
      "stepText": "Provide for patient privacy",
      "detailedTagText": "Provide for patient privacy (close the curtain, door, or privacy screen).",
      "tagCategory": "Opening",
      "phaseWord": "Approach",
      "clinicalNote": "",
      "subSteps": [],
      "criticalCategory": "privacy",
      "examScorecard": "",
      "icon": "🟢🪟",
      "boilerplateId": "PRIVACY"
    },
    {
      "id": 3,
      "segment": "open",
      "stepText": "Perform hand hygiene",
      "detailedTagText": "Perform hand hygiene using the six-step technique for a minimum of 20 seconds with soap and water, or use an alcohol-based hand rub when hands are visibly clean.",
      "tagCategory": "Key Procedure",
      "phaseWord": "Approach",
      "clinicalNote": "",
      "subSteps": [],
      "criticalCategory": "hand-hygiene",
      "examScorecard": "",
      "icon": "🟢🧼",
      "boilerplateId": "HAND_HYGIENE"
    },
    {
      "id": 4,
      "segment": "core",
      "stepText": "Position patient supine; expose leg",
      "detailedTagText": "Position the patient in the supine position. Expose only the leg the candidate will be placing the stocking on.",
      "tagCategory": "Core",
      "phaseWord": "Apply",
      "clinicalNote": "",
      "subSteps": [],
      "criticalCategory": "",
      "examScorecard": "",
      "icon": "🔵"
    },
    {
      "id": 5,
      "segment": "core",
      "stepText": "Turn stocking inside out to heel",
      "detailedTagText": "Gather supplies and turn the stocking inside out to the heel.",
      "tagCategory": "Core",
      "phaseWord": "Apply",
      "clinicalNote": "",
      "subSteps": [],
      "criticalCategory": "",
      "examScorecard": "",
      "icon": "🔵"
    },
    {
      "id": 6,
      "segment": "core",
      "stepText": "Place stocking over toes and heel",
      "detailedTagText": "Place the stocking over the patient's toes, foot, and heel.",
      "tagCategory": "Core",
      "phaseWord": "Apply",
      "clinicalNote": "",
      "subSteps": [],
      "criticalCategory": "",
      "examScorecard": "",
      "icon": "🔵"
    },
    {
      "id": 7,
      "segment": "core",
      "stepText": "Pull stocking up the leg",
      "detailedTagText": "Gently pull the stocking up their leg.",
      "tagCategory": "Core",
      "phaseWord": "Apply",
      "clinicalNote": "",
      "subSteps": [],
      "criticalCategory": "",
      "examScorecard": "",
      "icon": "🔵"
    },
    {
      "id": 8,
      "segment": "core",
      "stepText": "Move foot/leg gently; avoid force",
      "detailedTagText": "Move foot and leg gently and naturally, avoiding force and over-extension of limb and joints.",
      "tagCategory": "Core",
      "phaseWord": "Apply",
      "clinicalNote": "",
      "subSteps": [],
      "criticalCategory": "",
      "examScorecard": "",
      "icon": "🔵"
    },
    {
      "id": 9,
      "segment": "core",
      "stepText": "Adjust stocking wrinkle-free to knee",
      "detailedTagText": "Adjust stocking; stocking should be wrinkle-free to the knee.",
      "tagCategory": "Core",
      "phaseWord": "Secure",
      "clinicalNote": "",
      "subSteps": [],
      "criticalCategory": "",
      "examScorecard": "",
      "icon": "🔵"
    },
    {
      "id": 10,
      "segment": "close",
      "stepText": "Call light; bed low and locked",
      "detailedTagText": "Place the call light (or signaling device) within reach of the patient. Lower the bed to its lowest position and verify the bed brakes are locked.",
      "tagCategory": "Closing",
      "phaseWord": "Secure",
      "clinicalNote": "",
      "subSteps": [],
      "criticalCategory": "bed-call-light",
      "examScorecard": "",
      "icon": "🔴🛏️🔔",
      "boilerplateId": "BED_LOW|CALL_LIGHT"
    },
    {
      "id": 11,
      "segment": "close",
      "stepText": "Perform hand hygiene",
      "detailedTagText": "Perform hand hygiene using the six-step technique for a minimum of 20 seconds with soap and water, or use an alcohol-based hand rub when hands are visibly clean.",
      "tagCategory": "Key Procedure",
      "phaseWord": "Secure",
      "clinicalNote": "",
      "subSteps": [],
      "criticalCategory": "hand-hygiene",
      "examScorecard": "",
      "icon": "🔴🧼",
      "boilerplateId": "HAND_HYGIENE"
    }
  ]
}
